aspectlib/__init__.py
aspectlib/contrib.py
aspectlib/debug.py
aspectlib/pytestsupport.py
aspectlib/test.py
aspectlib/utils.py
aspectlib-2.0.0.dist-info/AUTHORS.rst
aspectlib-2.0.0.dist-info/LICENSE
aspectlib-2.0.0.dist-info/METADATA
aspectlib-2.0.0.dist-info/WHEEL
aspectlib-2.0.0.dist-info/entry_points.txt
aspectlib-2.0.0.dist-info/top_level.txt
aspectlib-2.0.0.dist-info/RECORD
