Metadata-Version: 2.1
Name: aspectlib
Version: 2.0.0
Summary: ``aspectlib`` is an aspect-oriented programming, monkey-patch and decorators library. It is useful when changing
Home-page: https://github.com/ionelmc/python-aspectlib
Author: Ionel Cristian Mărieș
Author-email: contact@ionelmc.ro
License: BSD-2-Clause
Project-URL: Documentation, https://python-aspectlib.readthedocs.io/
Project-URL: Changelog, https://python-aspectlib.readthedocs.io/en/latest/changelog.html
Project-URL: Issue Tracker, https://github.com/ionelmc/python-aspectlib/issues
Keywords: aop,aspects,aspect oriented programming,decorators,patch,monkeypatch,weave,debug,log,tests,mock,capture,replay,capture-replay,debugging,patching,monkeypatching,record,recording,mocking,logger
Platform: UNKNOWN
Classifier: Development Status :: 5 - Production/Stable
Classifier: Intended Audience :: Developers
Classifier: License :: OSI Approved :: BSD License
Classifier: Operating System :: Unix
Classifier: Operating System :: POSIX
Classifier: Operating System :: Microsoft :: Windows
Classifier: Programming Language :: Python
Classifier: Programming Language :: Python :: 3
Classifier: Programming Language :: Python :: 3 :: Only
Classifier: Programming Language :: Python :: 3.7
Classifier: Programming Language :: Python :: 3.8
Classifier: Programming Language :: Python :: 3.9
Classifier: Programming Language :: Python :: 3.10
Classifier: Programming Language :: Python :: Implementation :: CPython
Classifier: Programming Language :: Python :: Implementation :: PyPy
Classifier: Topic :: Utilities
Requires-Python: >=3.7
License-File: LICENSE
License-File: AUTHORS.rst
Requires-Dist: fields
